Comicsru.py
Comicsru-1.0.0.dist-info/LICENSE
Comicsru-1.0.0.dist-info/METADATA
Comicsru-1.0.0.dist-info/WHEEL
Comicsru-1.0.0.dist-info/top_level.txt
Comicsru-1.0.0.dist-info/RECORD
