Metadata-Version: 2.1
Name: Comicsru
Version: 1.0.0
Summary: A package to search and download comics on https://readcomicsonline.ru
Home-page: https://github.com/CYB3R-G0D/Comicsru
Author: Cyb3rG0d
Author-email: cyb3r-g0d.xrkbm@aleeas.com
License: UNKNOWN
Project-URL: Bug Tracker, https://github.com/CYB3R-G0D/Comicsru/issues
Platform: UNKNOWN
Classifier: Programming Language :: Python :: 3
Classifier: License :: OSI Approved :: MIT License
Classifier: Operating System :: OS Independent
Requires-Python: >=3.6
Requires-Dist: glob
Requires-Dist: img2pdf
Requires-Dist: beautifulsoup4
